lingo/__init__.py
lingo/__main__.py
lingo/argments.py
lingo/dataset.py
lingo/deepspeed_file.py
lingo/inference.py
lingo/initialize.py
lingo/lomo.py
lingo/lora.py
lingo/setting.py
lingo/trainer.py
lingo/utils.py
lingo/kernels/__init__.py
lingo/models/GLM130B_model.py
lingo/models/GPT2_model.py
lingo/models/GPTNeo_model.py
lingo/models/LLAMA_model.py
lingo/models/LLAMAv2_model.py
lingo/models/__init__.py
lingo/models/basemodel.py
lingo/models/model_io.py
lingo/models/transformers_model.py
lingo/quantization/__init__.py
lingo/quantization/functional.py
lingo/quantization/layers.py
lingo/scaled_rope/__init__.py
lingo/scaled_rope/configuration_llama.py
lingo/scaled_rope/modelling_llama.py
lingo_llm-1.2.0.dist-info/LICENSE
lingo_llm-1.2.0.dist-info/METADATA
lingo_llm-1.2.0.dist-info/WHEEL
lingo_llm-1.2.0.dist-info/top_level.txt
lingo_llm-1.2.0.dist-info/RECORD
